{
  "content": [
    {
      "content": null,
      "created": "2022-07-31T12:06:54.759194Z",
      "format": null,
      "last_modified": "2022-07-31T12:05:56.642309Z",
      "mimetype": "text/x-python",
      "name": "grading.py",
      "path": "mml-assignment/Week2-2/grading.py",
      "size": 1006,
      "type": "file",
      "writable": true
    },
    {
      "content": null,
      "created": "2022-07-31T12:06:54.759194Z",
      "format": null,
      "last_modified": "2022-07-31T12:05:56.642309Z",
      "mimetype": "image/jpeg",
      "name": "my_image.jpg",
      "path": "mml-assignment/Week2-2/my_image.jpg",
      "size": 90446,
      "type": "file",
      "writable": true
    },
    {
      "content": null,
      "created": "2022-07-31T12:06:54.759194Z",
      "format": null,
      "last_modified": "2022-07-31T12:05:56.642309Z",
      "mimetype": null,
      "name": "Week 2-2. Linear Algebra 2.ipynb",
      "path": "mml-assignment/Week2-2/Week 2-2. Linear Algebra 2.ipynb",
      "size": 329138,
      "type": "notebook",
      "writable": true
    },
    {
      "content": null,
      "created": "2022-07-31T12:06:54.759194Z",
      "format": null,
      "last_modified": "2022-07-31T12:05:56.642309Z",
      "mimetype": "image/png",
      "name": "linear_transform.png",
      "path": "mml-assignment/Week2-2/linear_transform.png",
      "size": 71212,
      "type": "file",
      "writable": true
    }
  ],
  "created": "2022-07-31T12:06:54.759194Z",
  "format": "json",
  "last_modified": "2022-07-31T12:06:54.759194Z",
  "mimetype": null,
  "name": "Week2-2",
  "path": "mml-assignment/Week2-2",
  "size": null,
  "type": "directory",
  "writable": true
}